gym_zelda_pygame/__init__.py
gym_zelda_pygame/adapter.py
gym_zelda_pygame/wrappers.py
gym_zelda_pygame/envs/__init__.py
gym_zelda_pygame/envs/zelda_env.py
gym_zelda_pygame/game/audio/Fire.wav
gym_zelda_pygame/game/audio/death.wav
gym_zelda_pygame/game/audio/heal.wav
gym_zelda_pygame/game/audio/hit.wav
gym_zelda_pygame/game/audio/main.ogg
gym_zelda_pygame/game/audio/sword.wav
gym_zelda_pygame/game/audio/attack/claw.wav
gym_zelda_pygame/game/audio/attack/fireball.wav
gym_zelda_pygame/game/audio/attack/slash.wav
gym_zelda_pygame/game/code/debug.py
gym_zelda_pygame/game/code/enemy.py
gym_zelda_pygame/game/code/entity.py
gym_zelda_pygame/game/code/level.py
gym_zelda_pygame/game/code/magic.py
gym_zelda_pygame/game/code/main.py
gym_zelda_pygame/game/code/particles.py
gym_zelda_pygame/game/code/player.py
gym_zelda_pygame/game/code/settings.py
gym_zelda_pygame/game/code/support.py
gym_zelda_pygame/game/code/tile.py
gym_zelda_pygame/game/code/ui.py
gym_zelda_pygame/game/code/upgrade.py
gym_zelda_pygame/game/code/weapon.py
gym_zelda_pygame/game/graphics/font/joystix.ttf
gym_zelda_pygame/game/graphics/grass/grass_1.png
gym_zelda_pygame/game/graphics/grass/grass_2.png
gym_zelda_pygame/game/graphics/grass/grass_3.png
gym_zelda_pygame/game/graphics/monsters/bamboo/attack/0.png
gym_zelda_pygame/game/graphics/monsters/bamboo/idle/0.png
gym_zelda_pygame/game/graphics/monsters/bamboo/idle/1.png
gym_zelda_pygame/game/graphics/monsters/bamboo/idle/2.png
gym_zelda_pygame/game/graphics/monsters/bamboo/idle/3.png
gym_zelda_pygame/game/graphics/monsters/bamboo/move/0.png
gym_zelda_pygame/game/graphics/monsters/bamboo/move/1.png
gym_zelda_pygame/game/graphics/monsters/bamboo/move/2.png
gym_zelda_pygame/game/graphics/monsters/bamboo/move/3.png
gym_zelda_pygame/game/graphics/monsters/raccoon/attack/0.png
gym_zelda_pygame/game/graphics/monsters/raccoon/attack/1.png
gym_zelda_pygame/game/graphics/monsters/raccoon/attack/2.png
gym_zelda_pygame/game/graphics/monsters/raccoon/attack/3.png
gym_zelda_pygame-0.1.9.dist-info/licenses/LICENSE
gym_zelda_pygame-0.1.9.dist-info/METADATA
gym_zelda_pygame-0.1.9.dist-info/WHEEL
gym_zelda_pygame-0.1.9.dist-info/top_level.txt
gym_zelda_pygame-0.1.9.dist-info/RECORD
