Metadata-Version: 2.4
Name: gym-zelda-pygame
Version: 0.1.9
Summary: A ROM-free Zelda-like Gymnasium environment built on Pygame.
Author: Henry LeCates
License: MIT License
Keywords: reinforcement-learning,gymnasium,pygame,zelda,rl,environment
Classifier: Development Status :: 3 - Alpha
Classifier: Intended Audience :: Science/Research
Classifier: License :: OSI Approved :: MIT License
Classifier: Programming Language :: Python :: 3
Classifier: Programming Language :: Python :: 3 :: Only
Classifier: Programming Language :: Python :: 3.9
Classifier: Programming Language :: Python :: 3.10
Classifier: Programming Language :: Python :: 3.11
Classifier: Operating System :: OS Independent
Classifier: Topic :: Scientific/Engineering :: Artificial Intelligence
Classifier: Topic :: Games/Entertainment
Requires-Python: >=3.9
License-File: LICENSE
Requires-Dist: gymnasium>=0.29
Requires-Dist: pygame>=2.5
Requires-Dist: numpy>=1.24
Requires-Dist: Pillow>=10.0
Provides-Extra: dev
Requires-Dist: pytest>=8; extra == "dev"
Requires-Dist: flake8>=7; extra == "dev"
Requires-Dist: build>=1; extra == "dev"
Requires-Dist: twine>=5; extra == "dev"
Dynamic: license-file
